waelpdf/__init__.py
waelpdf/pdf2image.py
waelpdf/pdf2text.py
waelpdf-0.1.dist-info/licenses/LICENSE
waelpdf-0.1.dist-info/METADATA
waelpdf-0.1.dist-info/WHEEL
waelpdf-0.1.dist-info/top_level.txt
waelpdf-0.1.dist-info/RECORD
