Metadata-Version: 2.4
Name: waelpdf
Version: 0.1
Summary: This The Readme file
License-File: LICENSE
Dynamic: license-file
Dynamic: summary
